pdots.py
pdots-0.3.0.dist-info/WHEEL
pdots-0.3.0.dist-info/METADATA
pdots-0.3.0.dist-info/RECORD
