Metadata-Version: 2.1
Name: pdots
Version: 0.3.0
Summary: Progress dots
Author: L3viathan
Author-email: git@l3vi.de
Requires-Python: >=3.9,<4.0
Classifier: Programming Language :: Python :: 3
Classifier: Programming Language :: Python :: 3.10
Classifier: Programming Language :: Python :: 3.9
